cypari2-2.2.0.dist-info/RECORD
cypari2-2.2.0.dist-info/WHEEL
cypari2-2.2.0.dist-info/LICENSE
cypari2-2.2.0.dist-info/top_level.txt
cypari2-2.2.0.dist-info/METADATA
cypari2/auto_paridecl.pxd
cypari2/convert.cpython-311-i386-linux-gnu.so
cypari2/types.pxd
cypari2/string_utils.pxd
cypari2/pari_instance.pxd
cypari2/string_utils.pyx
cypari2/gen.pyx
cypari2/handle_error.cpython-311-i386-linux-gnu.so
cypari2/custom_block.cpython-311-i386-linux-gnu.so
cypari2/closure.cpython-311-i386-linux-gnu.so
cypari2/paridecl.pxd
cypari2/gen.pxd
cypari2/pycore_long.pxd
cypari2/convert.pxd
cypari2/closure.pyx
cypari2/__init__.py
cypari2/stack.pxd
cypari2/convert.pyx
cypari2/cypari.h
cypari2/pari_instance.pyx
cypari2/handle_error.pxd
cypari2/stack.pyx
cypari2/pycore_long.h
cypari2/closure.pxd
cypari2/pari_instance.cpython-311-i386-linux-gnu.so
cypari2/string_utils.cpython-311-i386-linux-gnu.so
cypari2/paripriv.pxd
cypari2/gen.cpython-311-i386-linux-gnu.so
cypari2/stack.cpython-311-i386-linux-gnu.so
cypari2/custom_block.pyx
cypari2/handle_error.pyx
cypari2.libs/libpari-gmp-tls-e7bc21d2.so.2.15.4
cypari2.libs/libgmp-b369507c.so.10.5.0
