Metadata-Version: 2.1
Name: cypari2
Version: 2.2.0
Summary: A Python interface to the number theory library PARI/GP
Author: Luca De Feo, Vincent Delecroix, Jeroen Demeyer, Vincent Klein
Maintainer-email: SageMath developers <sage-devel@googlegroups.com>
License: GNU General Public License, version 2 or later
Project-URL: Homepage, https://github.com/sagemath/cypari2
Keywords: PARI/GP number theory
Requires-Python: >=3.9
License-File: LICENSE
Requires-Dist: cysignals>=1.11.3
